{"type":"Scene","props":{"width":1334,"height":750},"compId":2,"child":[{"type":"Sprite","props":{"x":-150,"alpha":0.5},"compId":6,"child":[{"type":"Rect","props":{"width":1634,"lineWidth":1,"height":750,"fillColor":"#000000"},"compId":7}]},{"type":"Sprite","props":{"y":300,"x":592,"width":150,"height":150},"compId":11,"child":[{"type":"Rect","props":{"width":150,"lineWidth":1,"height":150,"fillColor":"#000000"},"compId":12}]},{"type":"Sprite","props":{"y":350,"x":667,"width":100,"var":"progressView","texture":"local/loading/loading.png","pivotY":50,"pivotX":50,"height":100},"compId":3},{"type":"Label","props":{"y":396,"var":"lblProgress","text":"0%","fontSize":25,"color":"#ffffff","centerX":0,"align":"center"},"compId":4},{"type":"Script","props":{"type":"waiting","progressViewBg":"@node:11","progressView":"@node:3","lblProgress":"@node:4","runtime":"scripts/common/Loading/LoadingControl.js"},"compId":8}],"loadList":["local/loading/loading.png"],"loadList3D":[]}